odoo/addons/product_set_sell_only_by_packaging/README.rst
odoo/addons/product_set_sell_only_by_packaging/__init__.py
odoo/addons/product_set_sell_only_by_packaging/__manifest__.py
odoo/addons/product_set_sell_only_by_packaging/data/ir_cron.xml
odoo/addons/product_set_sell_only_by_packaging/i18n/es.po
odoo/addons/product_set_sell_only_by_packaging/i18n/it.po
odoo/addons/product_set_sell_only_by_packaging/i18n/product_set_sell_only_by_packaging.pot
odoo/addons/product_set_sell_only_by_packaging/models/__init__.py
odoo/addons/product_set_sell_only_by_packaging/models/product_product.py
odoo/addons/product_set_sell_only_by_packaging/models/product_set_line.py
odoo/addons/product_set_sell_only_by_packaging/models/product_template.py
odoo/addons/product_set_sell_only_by_packaging/readme/CONTRIBUTORS.md
odoo/addons/product_set_sell_only_by_packaging/readme/CREDITS.md
odoo/addons/product_set_sell_only_by_packaging/readme/DESCRIPTION.md
odoo/addons/product_set_sell_only_by_packaging/static/description/icon.png
odoo/addons/product_set_sell_only_by_packaging/static/description/index.html
odoo/addons/product_set_sell_only_by_packaging/tests/__init__.py
odoo/addons/product_set_sell_only_by_packaging/tests/test_product_set_packaging.py
odoo/addons/product_set_sell_only_by_packaging/views/product_set_line.xml
odoo/addons/product_set_sell_only_by_packaging/views/product_template.xml
odoo_addon_product_set_sell_only_by_packaging-18.0.1.0.0.4.dist-info/METADATA
odoo_addon_product_set_sell_only_by_packaging-18.0.1.0.0.4.dist-info/WHEEL
odoo_addon_product_set_sell_only_by_packaging-18.0.1.0.0.4.dist-info/top_level.txt
odoo_addon_product_set_sell_only_by_packaging-18.0.1.0.0.4.dist-info/RECORD
