Metadata-Version: 2.1
Name: odoo-addon-product_set_sell_only_by_packaging
Version: 18.0.1.0.0.4
Requires-Python: >=3.10
Requires-Dist: odoo-addon-sale_product_set_packaging_qty==18.0.*
Requires-Dist: odoo-addon-sell_only_by_packaging==18.0.*
Requires-Dist: odoo==18.0.*
Summary: Glue module between `sell_only_by_packaging` and `sale_product_set_packaging_qty`.
Home-page: https://github.com/OCA/sale-workflow
License: AGPL-3
Author: Camptocamp, Odoo Community Association (OCA)
Author-email: support@odoo-community.org
Classifier: Programming Language :: Python
Classifier: Framework :: Odoo
Classifier: Framework :: Odoo :: 18.0
Classifier: License :: OSI Approved :: GNU Affero General Public License v3
Classifier: Development Status :: 3 - Alpha
